LICENSE.md
README.md
setup.py
imdb_api/__init__.py
imdb_page_api.egg-info/PKG-INFO
imdb_page_api.egg-info/SOURCES.txt
imdb_page_api.egg-info/dependency_links.txt
imdb_page_api.egg-info/not-zip-safe
imdb_page_api.egg-info/requires.txt
imdb_page_api.egg-info/top_level.txt