Metadata-Version: 2.1
Name: imdb-page-api
Version: 1.0.2
Summary: A useful API to scrap movie/series/video details available on IMDb.
Home-page: https://github.com/BlaxPanther/imdb-api.git
Author: BlaxPanther
License: GNU General Public License v3.0
Keywords: python,imdb,movie-api,imdb-webscrapping,imdb-api,imdb-python,imdb-scraper
Platform: UNKNOWN
Classifier: Programming Language :: Python :: 3.4
Classifier: Programming Language :: Python :: 3.5
Classifier: Programming Language :: Python :: 3.6
Classifier: Topic :: Internet :: WWW/HTTP
License-File: LICENSE.md
